fadtk/__init__.py
fadtk/__main__.py
fadtk/embeds.py
fadtk/fad.py
fadtk/fad_batch.py
fadtk/model_loader.py
fadtk/package.py
fadtk/utils.py
fadtk/stats/fma_pop.npz
fadtk/test/__init__.py
fadtk/test/__main__.py
fadtk/test/samples_FAD_scores.csv
fadtk/test/test_cleanup.sh
fadtk/test/samples/mg-1634.opus
fadtk/test/samples/mg-1648.opus
fadtk/test/samples/mg-1741.opus
fadtk/test/samples/mg-2344.opus
fadtk/test/samples/mg-2551.opus
fadtk/test/samples/mg-2759.opus
fadtk/test/samples/mg-284.opus
fadtk/test/samples/mg-483.opus
fadtk/test/samples/mg-66.opus
fadtk/test/samples/mg-911.opus
fadtk/test/samples/mg-974.opus
fadtk/test/samples/mlm-1619.opus
fadtk/test/samples/mlm-1698.opus
fadtk/test/samples/mlm-2940.opus
fadtk/test/samples/mlm-483.opus
fadtk/test/samples/mlm-974.opus
fadtk/test/samples/mubert-130.opus
fadtk/test/samples/mubert-1348.opus
fadtk/test/samples/mubert-1619.opus
fadtk/test/samples/mubert-2120.opus
fadtk/test/samples/mubert-2545.opus
fadtk/test/samples/mubert-2701.opus
fadtk/test/samples/mubert-806.opus
fadtk-1.1.0.dist-info/METADATA
fadtk-1.1.0.dist-info/WHEEL
fadtk-1.1.0.dist-info/entry_points.txt
fadtk-1.1.0.dist-info/licenses/LICENSE
fadtk-1.1.0.dist-info/RECORD
