Metadata-Version: 2.4
Name: fadtk
Version: 1.1.0
Summary: A simple and standardized library for Frechet Audio Distance calculation.
Project-URL: Homepage, https://github.com/Microsoft/fadtk
Project-URL: Repository, https://github.com/Microsoft/fadtk
Author-email: Azalea <me@hydev.org>
License-File: LICENSE
Requires-Python: <=3.13,>=3.10
Requires-Dist: audioread>=3.0.1
Requires-Dist: encodec<1,>=0.1.1
Requires-Dist: hypy-utils<2,>=1.0.19
Requires-Dist: laion-clap<2,>=1.1.6
Requires-Dist: librosa<1,>=0.10.1
Requires-Dist: llvmlite>=0.44
Requires-Dist: msclap>=1.3.4
Requires-Dist: nnaudio<1,>=0.3.2
Requires-Dist: numpy<2
Requires-Dist: pandas<3,>=2.0.3
Requires-Dist: resampy
Requires-Dist: scipy<2,>=1.11.2
Requires-Dist: soundfile<1,>=0.12.1
Requires-Dist: torch<3,>=2.3.0
Requires-Dist: torchvision>=0.22.0
Requires-Dist: transformers<5,>=4.30.0
Requires-Dist: wheel<1,>=0.41.1
